{
    "1": {
        "qestion": "年齢",
        "answer": [
            "65歳未満",
            "65歳以上"
        ],
        "importance": "3"
    },
    "2": {
        "qestion": "性別",
        "answer": [
            "男性",
            "女性"
        ],
        "importance": "1"
    },
    "3": {
        "qestion": "胸の痛みはありますか。",
        "answer": [
            "はい",
            "いいえ"
        ],
        "importance": "2"
    },
    "4": {
        "qestion": "めまいやふらつき、息切れはありますか。",
        "answer": [
            "はい",
            "いいえ"
        ],
        "importance": "3"
    },
    "5": {
        "qestion": "頭痛はありますか。",
        "answer": [
            "はい",
            "いいえ"
        ],
        "importance": "2"
    },
    "6": {
        "qestion": "意識を失ったことはありますか。",
        "answer": [
            "はい",
            "いいえ"
        ],
        "importance": "4"
    },
    "7": {
        "qestion": "以前にも同様の症状はありましたか。",
        "answer": [
            "はい",
            "いいえ"
        ],
        "importance": "4"
    },
    "8": {
        "qestion": "いつからありますか。",
        "answer": [
            "最近",
            "少し前",
            "数ヶ月前"
        ],
        "importance": "3"
    },
    "9": {
        "qestion": "頻度はどれくらいですか。",
        "answer": [
            "毎日",
            "月に一回くらい",
            "数か月に一回くらい"
        ],
        "importance": "3"
    },
    "10": {
        "qestion": "頻度は増加してますか。",
        "answer": [
            "している",
            "していない"
        ],
        "importance": "4"
    },
    "11": {
        "qestion": "日中か夜間、どちらが多いですか。",
        "answer": [
            "日中",
            "夜間"
        ],
        "importance": "4"
    },
    "12": {
        "qestion": "動悸は、どのような症状ですか。脈が飛ぶような症状ですか。とん、とん、ととん、とん、とん。。。ですか？",
        "answer": [
            "はい",
            "いいえ"
        ],
        "importance": "5"
    },
    "13": {
        "qestion": "動悸は、どのような症状ですか。脈が速くなるような症状ですか。どどどどどどどど。。。",
        "answer": [
            "はい",
            "いいえ"
        ],
        "importance": "5"
    },
    "14": {
        "qestion": "動悸は、どのような症状ですか。脈が強く打つような症状ですか。どくん、どくん、どくん。。。",
        "answer": [
            "はい",
            "いいえ"
        ],
        "importance": "5"
    },
    "15": {
        "qestion": "動悸は、どのような症状ですか。脈が乱れるような症状ですか。ど、どどど、どど、ど、どどど、どど。",
        "answer": [
            "はい",
            "いいえ"
        ],
        "importance": "5"
    },
    "16": {
        "qestion": "発作は、突然はじまりますか。",
        "answer": [
            "はい",
            "いいえ"
        ],
        "importance": "4"
    },
    "17": {
        "qestion": "突然おわりますか。",
        "answer": [
            "はい",
            "いいえ"
        ],
        "importance": "4"
    },
    "18": {
        "qestion": "発作が起こりそうな予感はありますか。",
        "answer": [
            "はい",
            "いいえ"
        ],
        "importance": "3"
    },
    "19": {
        "qestion": "息こらえや息どめするととまりますか。",
        "answer": [
            "はい",
            "いいえ"
        ],
        "importance": "3"
    },
}